diceroll/__init__.py
diceroll/rolling.py
diceroll_RPG/__init__.py
diceroll_RPG/rolling.py
diceroll_RPG-0.0.1.dist-info/METADATA
diceroll_RPG-0.0.1.dist-info/WHEEL
diceroll_RPG-0.0.1.dist-info/top_level.txt
diceroll_RPG-0.0.1.dist-info/RECORD
