Metadata-Version: 2.1
Name: diceroll_RPG
Version: 0.0.1
Summary: An application to roll dices
Home-page: https://github.com/Igor-Wolf/DiceRoll_RPG/tree/main
Author: Igor Reis Barbosa
Requires-Python: >=3.1
